{
  "objectInfo" : {
    "id" : "9kxxQjY5byah5eGL95rgIs",
    "name" : "Versioned_Project特別",
    "type" : "Project",
    "metadata" : {
      "modelVersion" : {
        "major" : 0,
        "minor" : 0
      },
      "repoInfo" : null,
      "contextAttributes" : [ ],
      "additionalInfo" : {
        "description" : "",
        "contentType" : "Binary",
        "documentState" : "COMPLETE"
      }
    }
  },
  "dataFileExtension" : "json",
  "updateTime" : "2023-08-21T05:39:48.427Z",
  "objectRefs" : [ ]
}